bmi_test.py
Min_BMI_Test-0.0.0.1.dist-info/METADATA
Min_BMI_Test-0.0.0.1.dist-info/WHEEL
Min_BMI_Test-0.0.0.1.dist-info/top_level.txt
Min_BMI_Test-0.0.0.1.dist-info/RECORD
