Metadata-Version: 2.1
Name: Min-BMI-Test
Version: 0.0.0.1
Summary: My First Test Package
Home-page: https://naver.com
Author: Sungmin Joo
Author-email: jsm1910486@gmail.com
License: MIT
Platform: UNKNOWN
Requires-Python: >=3
